uconfig.py
uconfig-0.1.1.dist-info/DESCRIPTION.rst
uconfig-0.1.1.dist-info/METADATA
uconfig-0.1.1.dist-info/RECORD
uconfig-0.1.1.dist-info/WHEEL
uconfig-0.1.1.dist-info/metadata.json
uconfig-0.1.1.dist-info/top_level.txt
