Metadata-Version: 2.0
Name: uconfig
Version: 0.1.1
Summary: simple configuration file parser
Home-page: https://bitbucket.org/uranoxyd/uconfig
Author: David Ewelt
Author-email: uranoxyd@gmail.com
License: BSD
Keywords: configuration parser
Platform: UNKNOWN
Classifier: Development Status :: 3 - Alpha
Classifier: Intended Audience :: Developers
Classifier: Topic :: Software Development :: Libraries :: Python Modules
Classifier: Programming Language :: Python :: 2
Classifier: Programming Language :: Python :: 2.7
Classifier: Programming Language :: Python :: 3
